<?xml version="1.0" ?>
<gpx xmlns="http://www.topografix.com/GPX/1/1">
 <trk>
  <name>
   PALM 35 6th Day, Hale to Oscoda
  </name>
  <trkseg>
   <trkpt lat="44.37803" lon="-83.79765"/>
   <trkpt lat="44.37803" lon="-83.79764"/>
   <trkpt lat="44.37803" lon="-83.79764"/>
   <trkpt lat="44.37804" lon="-83.79468"/>
   <trkpt lat="44.37785" lon="-83.78471"/>
   <trkpt lat="44.37792" lon="-83.77451"/>
   <trkpt lat="44.37796" lon="-83.77193"/>
   <trkpt lat="44.37802" lon="-83.76944"/>
   <trkpt lat="44.37808" lon="-83.76588"/>
   <trkpt lat="44.37812" lon="-83.76469"/>
   <trkpt lat="44.37817" lon="-83.76205"/>
   <trkpt lat="44.37842" lon="-83.7541"/>
   <trkpt lat="44.37874" lon="-83.74478"/>
   <trkpt lat="44.3788" lon="-83.74216"/>
   <trkpt lat="44.37894" lon="-83.73737"/>
   <trkpt lat="44.37896" lon="-83.73569"/>
   <trkpt lat="44.3789" lon="-83.73509"/>
   <trkpt lat="44.3789" lon="-83.73509"/>
   <trkpt lat="44.37883" lon="-83.73479"/>
   <trkpt lat="44.37872" lon="-83.73449"/>
   <trkpt lat="44.37858" lon="-83.73422"/>
   <trkpt lat="44.37626" lon="-83.73071"/>
   <trkpt lat="44.37611" lon="-83.73039"/>
   <trkpt lat="44.37597" lon="-83.72991"/>
   <trkpt lat="44.37591" lon="-83.7296"/>
   <trkpt lat="44.37565" lon="-83.72763"/>
   <trkpt lat="44.37551" lon="-83.7266"/>
   <trkpt lat="44.37551" lon="-83.7266"/>
   <trkpt lat="44.37519" lon="-83.72411"/>
   <trkpt lat="44.37487" lon="-83.72205"/>
   <trkpt lat="44.3743" lon="-83.71875"/>
   <trkpt lat="44.3741" lon="-83.7173"/>
   <trkpt lat="44.37383" lon="-83.7153"/>
   <trkpt lat="44.37367" lon="-83.71467"/>
   <trkpt lat="44.37352" lon="-83.71424"/>
   <trkpt lat="44.37255" lon="-83.71175"/>
   <trkpt lat="44.37244" lon="-83.71138"/>
   <trkpt lat="44.37237" lon="-83.71104"/>
   <trkpt lat="44.37233" lon="-83.71042"/>
   <trkpt lat="44.37239" lon="-83.70766"/>
   <trkpt lat="44.37248" lon="-83.70414"/>
   <trkpt lat="44.37247" lon="-83.7038"/>
   <trkpt lat="44.37244" lon="-83.70346"/>
   <trkpt lat="44.37236" lon="-83.70314"/>
   <trkpt lat="44.37219" lon="-83.70271"/>
   <trkpt lat="44.36948" lon="-83.69707"/>
   <trkpt lat="44.36898" lon="-83.69604"/>
   <trkpt lat="44.36878" lon="-83.69571"/>
   <trkpt lat="44.36858" lon="-83.69548"/>
   <trkpt lat="44.3653" lon="-83.69245"/>
   <trkpt lat="44.36415" lon="-83.69138"/>
   <trkpt lat="44.36397" lon="-83.69125"/>
   <trkpt lat="44.36369" lon="-83.69112"/>
   <trkpt lat="44.36235" lon="-83.69064"/>
   <trkpt lat="44.36102" lon="-83.6902"/>
   <trkpt lat="44.36067" lon="-83.69013"/>
   <trkpt lat="44.3594" lon="-83.69005"/>
   <trkpt lat="44.3594" lon="-83.69005"/>
   <trkpt lat="44.35533" lon="-83.68991"/>
   <trkpt lat="44.35477" lon="-83.68987"/>
   <trkpt lat="44.35454" lon="-83.68983"/>
   <trkpt lat="44.35435" lon="-83.68978"/>
   <trkpt lat="44.35396" lon="-83.68962"/>
   <trkpt lat="44.35308" lon="-83.68926"/>
   <trkpt lat="44.35126" lon="-83.68845"/>
   <trkpt lat="44.35106" lon="-83.68838"/>
   <trkpt lat="44.35087" lon="-83.68833"/>
   <trkpt lat="44.35037" lon="-83.68829"/>
   <trkpt lat="44.3493" lon="-83.68831"/>
   <trkpt lat="44.34862" lon="-83.68835"/>
   <trkpt lat="44.34823" lon="-83.68846"/>
   <trkpt lat="44.34786" lon="-83.68869"/>
   <trkpt lat="44.34668" lon="-83.6896"/>
   <trkpt lat="44.34497" lon="-83.6909"/>
   <trkpt lat="44.34466" lon="-83.69106"/>
   <trkpt lat="44.34451" lon="-83.69113"/>
   <trkpt lat="44.34429" lon="-83.69117"/>
   <trkpt lat="44.34398" lon="-83.69117"/>
   <trkpt lat="44.34378" lon="-83.69115"/>
   <trkpt lat="44.34356" lon="-83.69108"/>
   <trkpt lat="44.34338" lon="-83.69101"/>
   <trkpt lat="44.34324" lon="-83.69092"/>
   <trkpt lat="44.34291" lon="-83.69066"/>
   <trkpt lat="44.3426" lon="-83.69025"/>
   <trkpt lat="44.34243" lon="-83.68992"/>
   <trkpt lat="44.34176" lon="-83.68803"/>
   <trkpt lat="44.34114" lon="-83.68625"/>
   <trkpt lat="44.34089" lon="-83.68565"/>
   <trkpt lat="44.34066" lon="-83.68529"/>
   <trkpt lat="44.34041" lon="-83.68498"/>
   <trkpt lat="44.34012" lon="-83.68474"/>
   <trkpt lat="44.33986" lon="-83.68461"/>
   <trkpt lat="44.33963" lon="-83.68454"/>
   <trkpt lat="44.33921" lon="-83.68449"/>
   <trkpt lat="44.33764" lon="-83.68449"/>
   <trkpt lat="44.33736" lon="-83.68445"/>
   <trkpt lat="44.3371" lon="-83.68433"/>
   <trkpt lat="44.33682" lon="-83.68415"/>
   <trkpt lat="44.33644" lon="-83.68382"/>
   <trkpt lat="44.33569" lon="-83.68311"/>
   <trkpt lat="44.33487" lon="-83.68232"/>
   <trkpt lat="44.3347" lon="-83.68213"/>
   <trkpt lat="44.33425" lon="-83.6814"/>
   <trkpt lat="44.33397" lon="-83.68091"/>
   <trkpt lat="44.33389" lon="-83.68073"/>
   <trkpt lat="44.3339" lon="-83.68"/>
   <trkpt lat="44.33393" lon="-83.67856"/>
   <trkpt lat="44.33411" lon="-83.67667"/>
   <trkpt lat="44.33423" lon="-83.67569"/>
   <trkpt lat="44.33414" lon="-83.67445"/>
   <trkpt lat="44.3341" lon="-83.6735"/>
   <trkpt lat="44.33395" lon="-83.67168"/>
   <trkpt lat="44.33357" lon="-83.66979"/>
   <trkpt lat="44.33348" lon="-83.66921"/>
   <trkpt lat="44.33343" lon="-83.66877"/>
   <trkpt lat="44.33341" lon="-83.66834"/>
   <trkpt lat="44.33344" lon="-83.66805"/>
   <trkpt lat="44.33354" lon="-83.66774"/>
   <trkpt lat="44.33365" lon="-83.66754"/>
   <trkpt lat="44.33396" lon="-83.66713"/>
   <trkpt lat="44.33425" lon="-83.66683"/>
   <trkpt lat="44.33457" lon="-83.66643"/>
   <trkpt lat="44.33469" lon="-83.66625"/>
   <trkpt lat="44.33475" lon="-83.66612"/>
   <trkpt lat="44.33472" lon="-83.66597"/>
   <trkpt lat="44.33437" lon="-83.66505"/>
   <trkpt lat="44.33437" lon="-83.66505"/>
   <trkpt lat="44.33432" lon="-83.66483"/>
   <trkpt lat="44.33416" lon="-83.66339"/>
   <trkpt lat="44.33415" lon="-83.66285"/>
   <trkpt lat="44.33418" lon="-83.66239"/>
   <trkpt lat="44.33423" lon="-83.66202"/>
   <trkpt lat="44.33433" lon="-83.66156"/>
   <trkpt lat="44.33437" lon="-83.66126"/>
   <trkpt lat="44.33434" lon="-83.66086"/>
   <trkpt lat="44.33495" lon="-83.66027"/>
   <trkpt lat="44.3352" lon="-83.66004"/>
   <trkpt lat="44.33572" lon="-83.65963"/>
   <trkpt lat="44.33663" lon="-83.65876"/>
   <trkpt lat="44.3369" lon="-83.6585"/>
   <trkpt lat="44.33692" lon="-83.65842"/>
   <trkpt lat="44.33716" lon="-83.6579"/>
   <trkpt lat="44.33754" lon="-83.65679"/>
   <trkpt lat="44.33791" lon="-83.65595"/>
   <trkpt lat="44.3386" lon="-83.65542"/>
   <trkpt lat="44.33902" lon="-83.65517"/>
   <trkpt lat="44.33951" lon="-83.65469"/>
   <trkpt lat="44.34035" lon="-83.65345"/>
   <trkpt lat="44.34069" lon="-83.65306"/>
   <trkpt lat="44.34102" lon="-83.65236"/>
   <trkpt lat="44.34112" lon="-83.65186"/>
   <trkpt lat="44.34135" lon="-83.65147"/>
   <trkpt lat="44.34147" lon="-83.65127"/>
   <trkpt lat="44.34174" lon="-83.65097"/>
   <trkpt lat="44.34201" lon="-83.65049"/>
   <trkpt lat="44.34216" lon="-83.6501"/>
   <trkpt lat="44.34237" lon="-83.64944"/>
   <trkpt lat="44.34249" lon="-83.64921"/>
   <trkpt lat="44.34287" lon="-83.64797"/>
   <trkpt lat="44.34311" lon="-83.64735"/>
   <trkpt lat="44.34362" lon="-83.64587"/>
   <trkpt lat="44.344" lon="-83.64532"/>
   <trkpt lat="44.34428" lon="-83.64498"/>
   <trkpt lat="44.34521" lon="-83.64403"/>
   <trkpt lat="44.34552" lon="-83.6438"/>
   <trkpt lat="44.34562" lon="-83.64369"/>
   <trkpt lat="44.34595" lon="-83.64361"/>
   <trkpt lat="44.34613" lon="-83.64359"/>
   <trkpt lat="44.34664" lon="-83.64395"/>
   <trkpt lat="44.34707" lon="-83.64432"/>
   <trkpt lat="44.34736" lon="-83.64452"/>
   <trkpt lat="44.3477" lon="-83.64447"/>
   <trkpt lat="44.34788" lon="-83.64442"/>
   <trkpt lat="44.34811" lon="-83.64429"/>
   <trkpt lat="44.34825" lon="-83.64413"/>
   <trkpt lat="44.34838" lon="-83.64394"/>
   <trkpt lat="44.34851" lon="-83.64359"/>
   <trkpt lat="44.34878" lon="-83.64227"/>
   <trkpt lat="44.34896" lon="-83.64119"/>
   <trkpt lat="44.34858" lon="-83.6402"/>
   <trkpt lat="44.34816" lon="-83.63928"/>
   <trkpt lat="44.34801" lon="-83.63895"/>
   <trkpt lat="44.34775" lon="-83.63834"/>
   <trkpt lat="44.34751" lon="-83.63816"/>
   <trkpt lat="44.34751" lon="-83.63816"/>
   <trkpt lat="44.34737" lon="-83.63805"/>
   <trkpt lat="44.34634" lon="-83.63766"/>
   <trkpt lat="44.3454" lon="-83.63738"/>
   <trkpt lat="44.34444" lon="-83.63694"/>
   <trkpt lat="44.34346" lon="-83.63637"/>
   <trkpt lat="44.34273" lon="-83.63609"/>
   <trkpt lat="44.34175" lon="-83.63576"/>
   <trkpt lat="44.34069" lon="-83.63519"/>
   <trkpt lat="44.34086" lon="-83.63486"/>
   <trkpt lat="44.34141" lon="-83.63396"/>
   <trkpt lat="44.3419" lon="-83.63302"/>
   <trkpt lat="44.3424" lon="-83.63185"/>
   <trkpt lat="44.3425" lon="-83.63125"/>
   <trkpt lat="44.34261" lon="-83.63075"/>
   <trkpt lat="44.34266" lon="-83.63032"/>
   <trkpt lat="44.34267" lon="-83.63014"/>
   <trkpt lat="44.34291" lon="-83.6287"/>
   <trkpt lat="44.34314" lon="-83.62779"/>
   <trkpt lat="44.34339" lon="-83.62699"/>
   <trkpt lat="44.34356" lon="-83.62662"/>
   <trkpt lat="44.34369" lon="-83.62624"/>
   <trkpt lat="44.34382" lon="-83.62591"/>
   <trkpt lat="44.34408" lon="-83.62558"/>
   <trkpt lat="44.34479" lon="-83.62506"/>
   <trkpt lat="44.3451" lon="-83.62486"/>
   <trkpt lat="44.34529" lon="-83.62468"/>
   <trkpt lat="44.34646" lon="-83.6239"/>
   <trkpt lat="44.34761" lon="-83.62302"/>
   <trkpt lat="44.34834" lon="-83.62247"/>
   <trkpt lat="44.34916" lon="-83.62201"/>
   <trkpt lat="44.34916" lon="-83.62201"/>
   <trkpt lat="44.34937" lon="-83.62189"/>
   <trkpt lat="44.34967" lon="-83.62165"/>
   <trkpt lat="44.34985" lon="-83.62146"/>
   <trkpt lat="44.35011" lon="-83.62125"/>
   <trkpt lat="44.35069" lon="-83.62071"/>
   <trkpt lat="44.35127" lon="-83.62012"/>
   <trkpt lat="44.35193" lon="-83.61949"/>
   <trkpt lat="44.35248" lon="-83.61905"/>
   <trkpt lat="44.35279" lon="-83.61884"/>
   <trkpt lat="44.35343" lon="-83.61826"/>
   <trkpt lat="44.35465" lon="-83.61721"/>
   <trkpt lat="44.35559" lon="-83.6164"/>
   <trkpt lat="44.35569" lon="-83.6162"/>
   <trkpt lat="44.35587" lon="-83.61576"/>
   <trkpt lat="44.35593" lon="-83.61528"/>
   <trkpt lat="44.35593" lon="-83.61446"/>
   <trkpt lat="44.35593" lon="-83.61348"/>
   <trkpt lat="44.35603" lon="-83.61255"/>
   <trkpt lat="44.35621" lon="-83.61183"/>
   <trkpt lat="44.3564" lon="-83.61025"/>
   <trkpt lat="44.35646" lon="-83.60955"/>
   <trkpt lat="44.35645" lon="-83.60922"/>
   <trkpt lat="44.3565" lon="-83.60813"/>
   <trkpt lat="44.35661" lon="-83.60732"/>
   <trkpt lat="44.35675" lon="-83.60686"/>
   <trkpt lat="44.35701" lon="-83.60646"/>
   <trkpt lat="44.3572" lon="-83.60624"/>
   <trkpt lat="44.35753" lon="-83.60592"/>
   <trkpt lat="44.35783" lon="-83.60576"/>
   <trkpt lat="44.35809" lon="-83.60546"/>
   <trkpt lat="44.35887" lon="-83.60489"/>
   <trkpt lat="44.35923" lon="-83.60455"/>
   <trkpt lat="44.35943" lon="-83.60427"/>
   <trkpt lat="44.35952" lon="-83.60398"/>
   <trkpt lat="44.35948" lon="-83.60385"/>
   <trkpt lat="44.35993" lon="-83.60411"/>
   <trkpt lat="44.36038" lon="-83.60443"/>
   <trkpt lat="44.36087" lon="-83.60487"/>
   <trkpt lat="44.36108" lon="-83.60501"/>
   <trkpt lat="44.3619" lon="-83.60573"/>
   <trkpt lat="44.36254" lon="-83.60621"/>
   <trkpt lat="44.36301" lon="-83.6065"/>
   <trkpt lat="44.36372" lon="-83.60674"/>
   <trkpt lat="44.36389" lon="-83.60676"/>
   <trkpt lat="44.36389" lon="-83.60676"/>
   <trkpt lat="44.36442" lon="-83.60682"/>
   <trkpt lat="44.36487" lon="-83.60677"/>
   <trkpt lat="44.36535" lon="-83.60662"/>
   <trkpt lat="44.36611" lon="-83.60628"/>
   <trkpt lat="44.36679" lon="-83.60599"/>
   <trkpt lat="44.36688" lon="-83.60597"/>
   <trkpt lat="44.36774" lon="-83.60539"/>
   <trkpt lat="44.36827" lon="-83.60499"/>
   <trkpt lat="44.36913" lon="-83.6045"/>
   <trkpt lat="44.36971" lon="-83.60419"/>
   <trkpt lat="44.37057" lon="-83.60365"/>
   <trkpt lat="44.37125" lon="-83.60323"/>
   <trkpt lat="44.37183" lon="-83.60289"/>
   <trkpt lat="44.37207" lon="-83.60275"/>
   <trkpt lat="44.37259" lon="-83.60255"/>
   <trkpt lat="44.37345" lon="-83.60229"/>
   <trkpt lat="44.37417" lon="-83.60232"/>
   <trkpt lat="44.37479" lon="-83.60241"/>
   <trkpt lat="44.37578" lon="-83.60284"/>
   <trkpt lat="44.37811" lon="-83.60383"/>
   <trkpt lat="44.37896" lon="-83.60422"/>
   <trkpt lat="44.37993" lon="-83.60466"/>
   <trkpt lat="44.38021" lon="-83.60473"/>
   <trkpt lat="44.38028" lon="-83.60481"/>
   <trkpt lat="44.38234" lon="-83.60574"/>
   <trkpt lat="44.38261" lon="-83.60584"/>
   <trkpt lat="44.38301" lon="-83.60607"/>
   <trkpt lat="44.38334" lon="-83.60633"/>
   <trkpt lat="44.38365" lon="-83.60669"/>
   <trkpt lat="44.38384" lon="-83.60691"/>
   <trkpt lat="44.38403" lon="-83.60721"/>
   <trkpt lat="44.38424" lon="-83.60767"/>
   <trkpt lat="44.38439" lon="-83.6081"/>
   <trkpt lat="44.38457" lon="-83.60898"/>
   <trkpt lat="44.38474" lon="-83.61012"/>
   <trkpt lat="44.38496" lon="-83.61114"/>
   <trkpt lat="44.38522" lon="-83.61198"/>
   <trkpt lat="44.38588" lon="-83.61309"/>
   <trkpt lat="44.38625" lon="-83.61351"/>
   <trkpt lat="44.38666" lon="-83.61391"/>
   <trkpt lat="44.38767" lon="-83.61482"/>
   <trkpt lat="44.38842" lon="-83.6155"/>
   <trkpt lat="44.38991" lon="-83.61717"/>
   <trkpt lat="44.39243" lon="-83.62017"/>
   <trkpt lat="44.39352" lon="-83.62148"/>
   <trkpt lat="44.39459" lon="-83.62266"/>
   <trkpt lat="44.39527" lon="-83.6234"/>
   <trkpt lat="44.39566" lon="-83.62368"/>
   <trkpt lat="44.39613" lon="-83.62389"/>
   <trkpt lat="44.39641" lon="-83.62391"/>
   <trkpt lat="44.3967" lon="-83.62403"/>
   <trkpt lat="44.39674" lon="-83.62402"/>
   <trkpt lat="44.39685" lon="-83.62399"/>
   <trkpt lat="44.39689" lon="-83.62396"/>
   <trkpt lat="44.39885" lon="-83.62406"/>
   <trkpt lat="44.40016" lon="-83.62394"/>
   <trkpt lat="44.40124" lon="-83.62396"/>
   <trkpt lat="44.40379" lon="-83.62404"/>
   <trkpt lat="44.41047" lon="-83.6241"/>
   <trkpt lat="44.41583" lon="-83.6242"/>
   <trkpt lat="44.41742" lon="-83.62423"/>
   <trkpt lat="44.42474" lon="-83.62424"/>
   <trkpt lat="44.42787" lon="-83.62416"/>
   <trkpt lat="44.43165" lon="-83.62415"/>
   <trkpt lat="44.43164" lon="-83.62199"/>
   <trkpt lat="44.43164" lon="-83.62177"/>
   <trkpt lat="44.43164" lon="-83.62177"/>
   <trkpt lat="44.43168" lon="-83.62124"/>
   <trkpt lat="44.43178" lon="-83.62069"/>
   <trkpt lat="44.43195" lon="-83.62011"/>
   <trkpt lat="44.43225" lon="-83.61935"/>
   <trkpt lat="44.43305" lon="-83.61823"/>
   <trkpt lat="44.43422" lon="-83.61691"/>
   <trkpt lat="44.43494" lon="-83.61599"/>
   <trkpt lat="44.43563" lon="-83.61523"/>
   <trkpt lat="44.43621" lon="-83.6145"/>
   <trkpt lat="44.4365" lon="-83.6141"/>
   <trkpt lat="44.43684" lon="-83.61354"/>
   <trkpt lat="44.43716" lon="-83.61267"/>
   <trkpt lat="44.43728" lon="-83.61221"/>
   <trkpt lat="44.43742" lon="-83.61146"/>
   <trkpt lat="44.43748" lon="-83.61043"/>
   <trkpt lat="44.43752" lon="-83.60645"/>
   <trkpt lat="44.43756" lon="-83.59999"/>
   <trkpt lat="44.43761" lon="-83.58809"/>
   <trkpt lat="44.43775" lon="-83.5866"/>
   <trkpt lat="44.43829" lon="-83.58364"/>
   <trkpt lat="44.43894" lon="-83.5803"/>
   <trkpt lat="44.43923" lon="-83.57871"/>
   <trkpt lat="44.43929" lon="-83.57787"/>
   <trkpt lat="44.43928" lon="-83.5769"/>
   <trkpt lat="44.43912" lon="-83.57501"/>
   <trkpt lat="44.43868" lon="-83.56999"/>
   <trkpt lat="44.43858" lon="-83.56889"/>
   <trkpt lat="44.43855" lon="-83.56811"/>
   <trkpt lat="44.43861" lon="-83.56746"/>
   <trkpt lat="44.43875" lon="-83.5668"/>
   <trkpt lat="44.43897" lon="-83.56615"/>
   <trkpt lat="44.43931" lon="-83.56548"/>
   <trkpt lat="44.44062" lon="-83.56352"/>
   <trkpt lat="44.44245" lon="-83.56062"/>
   <trkpt lat="44.44267" lon="-83.56019"/>
   <trkpt lat="44.4428" lon="-83.55982"/>
   <trkpt lat="44.44309" lon="-83.55892"/>
   <trkpt lat="44.44392" lon="-83.5553"/>
   <trkpt lat="44.44423" lon="-83.55374"/>
   <trkpt lat="44.44435" lon="-83.55283"/>
   <trkpt lat="44.44442" lon="-83.55147"/>
   <trkpt lat="44.44449" lon="-83.54926"/>
   <trkpt lat="44.44464" lon="-83.54248"/>
   <trkpt lat="44.44484" lon="-83.53596"/>
   <trkpt lat="44.44496" lon="-83.53496"/>
   <trkpt lat="44.44607" lon="-83.5295"/>
   <trkpt lat="44.44622" lon="-83.52856"/>
   <trkpt lat="44.44627" lon="-83.52766"/>
   <trkpt lat="44.44622" lon="-83.52699"/>
   <trkpt lat="44.44615" lon="-83.52642"/>
   <trkpt lat="44.4459" lon="-83.52513"/>
   <trkpt lat="44.44456" lon="-83.51862"/>
   <trkpt lat="44.44377" lon="-83.51485"/>
   <trkpt lat="44.44362" lon="-83.51383"/>
   <trkpt lat="44.44356" lon="-83.51304"/>
   <trkpt lat="44.44354" lon="-83.51213"/>
   <trkpt lat="44.44351" lon="-83.50586"/>
   <trkpt lat="44.44351" lon="-83.50192"/>
   <trkpt lat="44.44353" lon="-83.49793"/>
   <trkpt lat="44.44352" lon="-83.4953"/>
   <trkpt lat="44.44355" lon="-83.48911"/>
   <trkpt lat="44.44354" lon="-83.48763"/>
   <trkpt lat="44.44357" lon="-83.48615"/>
   <trkpt lat="44.44355" lon="-83.48427"/>
   <trkpt lat="44.44348" lon="-83.48373"/>
   <trkpt lat="44.44339" lon="-83.48323"/>
   <trkpt lat="44.44332" lon="-83.48295"/>
   <trkpt lat="44.44292" lon="-83.48199"/>
   <trkpt lat="44.4425" lon="-83.48124"/>
   <trkpt lat="44.44056" lon="-83.47834"/>
   <trkpt lat="44.44028" lon="-83.47796"/>
   <trkpt lat="44.43993" lon="-83.47753"/>
   <trkpt lat="44.43929" lon="-83.47671"/>
   <trkpt lat="44.43902" lon="-83.47638"/>
   <trkpt lat="44.43863" lon="-83.47583"/>
   <trkpt lat="44.43827" lon="-83.47515"/>
   <trkpt lat="44.43804" lon="-83.47447"/>
   <trkpt lat="44.43791" lon="-83.4739"/>
   <trkpt lat="44.43784" lon="-83.47333"/>
   <trkpt lat="44.43783" lon="-83.47275"/>
   <trkpt lat="44.43784" lon="-83.47243"/>
   <trkpt lat="44.43818" lon="-83.46937"/>
   <trkpt lat="44.43823" lon="-83.46842"/>
   <trkpt lat="44.43821" lon="-83.46786"/>
   <trkpt lat="44.43814" lon="-83.46722"/>
   <trkpt lat="44.43804" lon="-83.46666"/>
   <trkpt lat="44.43794" lon="-83.46625"/>
   <trkpt lat="44.43778" lon="-83.46575"/>
   <trkpt lat="44.43769" lon="-83.4655"/>
   <trkpt lat="44.43635" lon="-83.46241"/>
   <trkpt lat="44.43336" lon="-83.45523"/>
   <trkpt lat="44.43313" lon="-83.45474"/>
   <trkpt lat="44.43278" lon="-83.45405"/>
   <trkpt lat="44.43251" lon="-83.45361"/>
   <trkpt lat="44.43196" lon="-83.45279"/>
   <trkpt lat="44.43036" lon="-83.4505"/>
   <trkpt lat="44.42999" lon="-83.44993"/>
   <trkpt lat="44.42982" lon="-83.44958"/>
   <trkpt lat="44.42953" lon="-83.44887"/>
   <trkpt lat="44.42886" lon="-83.4468"/>
   <trkpt lat="44.42807" lon="-83.44443"/>
   <trkpt lat="44.42773" lon="-83.44339"/>
   <trkpt lat="44.42758" lon="-83.4429"/>
   <trkpt lat="44.42748" lon="-83.44242"/>
   <trkpt lat="44.42745" lon="-83.44202"/>
   <trkpt lat="44.42745" lon="-83.44163"/>
   <trkpt lat="44.42747" lon="-83.44133"/>
   <trkpt lat="44.42744" lon="-83.43773"/>
   <trkpt lat="44.42742" lon="-83.43721"/>
   <trkpt lat="44.42735" lon="-83.43673"/>
   <trkpt lat="44.42723" lon="-83.43627"/>
   <trkpt lat="44.42708" lon="-83.43577"/>
   <trkpt lat="44.42696" lon="-83.43545"/>
   <trkpt lat="44.42672" lon="-83.43495"/>
   <trkpt lat="44.42644" lon="-83.43442"/>
   <trkpt lat="44.4248" lon="-83.43166"/>
   <trkpt lat="44.42372" lon="-83.42979"/>
   <trkpt lat="44.42346" lon="-83.42925"/>
   <trkpt lat="44.42346" lon="-83.42925"/>
   <trkpt lat="44.42329" lon="-83.4288"/>
   <trkpt lat="44.42307" lon="-83.42794"/>
   <trkpt lat="44.42299" lon="-83.42747"/>
   <trkpt lat="44.42295" lon="-83.42695"/>
   <trkpt lat="44.42294" lon="-83.42652"/>
   <trkpt lat="44.42299" lon="-83.42492"/>
   <trkpt lat="44.42342" lon="-83.4211"/>
   <trkpt lat="44.42362" lon="-83.41906"/>
   <trkpt lat="44.42391" lon="-83.41603"/>
   <trkpt lat="44.4241" lon="-83.41419"/>
   <trkpt lat="44.42428" lon="-83.41289"/>
   <trkpt lat="44.42486" lon="-83.40918"/>
   <trkpt lat="44.42498" lon="-83.4083"/>
   <trkpt lat="44.42502" lon="-83.4075"/>
   <trkpt lat="44.425" lon="-83.39778"/>
   <trkpt lat="44.42498" lon="-83.38561"/>
   <trkpt lat="44.42496" lon="-83.37769"/>
  </trkseg>
 </trk>
</gpx>
